hubby/__init__.py
hubby/_version.py
hubby/cli.py
hubby/git_wrapper.py
hubby-0.3.0.dist-info/DESCRIPTION.rst
hubby-0.3.0.dist-info/METADATA
hubby-0.3.0.dist-info/RECORD
hubby-0.3.0.dist-info/WHEEL
hubby-0.3.0.dist-info/entry_points.txt
hubby-0.3.0.dist-info/metadata.json
hubby-0.3.0.dist-info/top_level.txt
tests/__init__.py
tests/conftest.py
tests/test_assignees.py
tests/test_core.py
tests/test_git_wrapper.py
tests/test_pull_requests.py
