Metadata-Version: 2.0
Name: hubby
Version: 0.3.0
Summary: Hub alternatives
Home-page: https://github.com/thusoy/hubby
Author: Tarjei Husøy
Author-email: git@thusoy.com
License: UNKNOWN
Platform: UNKNOWN
Classifier: Development Status :: 3 - Alpha
Classifier: Intended Audience :: Developers
Classifier: License :: OSI Approved :: MIT License
Classifier: Programming Language :: Python :: 3.3
Classifier: Programming Language :: Python :: 3.4
Classifier: Programming Language :: Python :: 3.5
Requires-Dist: argcomplete
Requires-Dist: requests
